NEATpy/__init__.py
NEATpy/backend.py
NEATpy/connection.py
NEATpy/connection_properties.py
NEATpy/endpoint.py
NEATpy/enumerations.py
NEATpy/framer.py
NEATpy/listener.py
NEATpy/message_context.py
NEATpy/message_framer.py
NEATpy/message_properties.py
NEATpy/preconnection.py
NEATpy/security_parameters.py
NEATpy/selection_properties.py
NEATpy/transport_properties.py
NEATpy/typeAliases.py
NEATpy/utils.py
neat_py-0.1.dist-info/LICENSE.txt
neat_py-0.1.dist-info/METADATA
neat_py-0.1.dist-info/WHEEL
neat_py-0.1.dist-info/top_level.txt
neat_py-0.1.dist-info/RECORD
